flake8_wagtail_no_serve.py
flake8_wagtail_no_serve-0.1.2.dist-info/LICENSE.txt
flake8_wagtail_no_serve-0.1.2.dist-info/METADATA
flake8_wagtail_no_serve-0.1.2.dist-info/WHEEL
flake8_wagtail_no_serve-0.1.2.dist-info/entry_points.txt
flake8_wagtail_no_serve-0.1.2.dist-info/top_level.txt
flake8_wagtail_no_serve-0.1.2.dist-info/RECORD
