Metadata-Version: 2.1
Name: flake8-wagtail-no-serve
Version: 0.1.2
Summary: Flake8 plugin that enforces not creating custom serve methods in inheritors from Wagtail's Page model
Home-page: https://github.com/octavenz/flake8-wagtail-no-serve
Author: Richard Campen
Author-email: richard@campen.co
License: BSD-3-Clause
Classifier: Environment :: Web Environment
Classifier: Framework :: Django
Classifier: Framework :: Wagtail
Classifier: Framework :: Wagtail :: 2
Classifier: Framework :: Wagtail :: 3
Classifier: Framework :: Wagtail :: 4
Classifier: Intended Audience :: Developers
Classifier: License :: OSI Approved :: BSD License
Classifier: Programming Language :: Python
Classifier: Programming Language :: Python :: 3
Classifier: Programming Language :: Python :: 3 :: Only
Classifier: Programming Language :: Python :: Implementation :: CPython
Classifier: Topic :: Internet :: WWW/HTTP
Classifier: Topic :: Internet :: WWW/HTTP :: Site Management
Requires-Python: >=3.7
License-File: LICENSE.txt
Requires-Dist: flake8 (>=3.7)
Requires-Dist: importlib-metadata (>=0.9) ; python_version < "3.8"
